qiskit_mcp_servers/__init__.py
qiskit_mcp_servers-0.3.0.dist-info/METADATA
qiskit_mcp_servers-0.3.0.dist-info/WHEEL
qiskit_mcp_servers-0.3.0.dist-info/licenses/LICENSE
qiskit_mcp_servers-0.3.0.dist-info/RECORD
