Metadata-Version: 2.4
Name: qiskit-mcp-servers
Version: 0.3.0
Summary: Model Context Protocol servers for IBM Quantum services and Qiskit
Project-URL: Homepage, https://github.com/Qiskit/mcp-servers
Project-URL: Repository, https://github.com/Qiskit/mcp-servers
Project-URL: Documentation, https://github.com/Qiskit/mcp-servers#readme
Project-URL: Bug Tracker, https://github.com/Qiskit/mcp-servers/issues
Author-email: "Quantum+AI Team. IBM Quantum" <Quantum.Plus.AI@ibm.com>
License: Apache-2.0
License-File: LICENSE
Keywords: ai,ibm,mcp,qiskit,quantum,quantum-computing
Classifier: Development Status :: 3 - Alpha
Classifier: Intended Audience :: Developers
Classifier: License :: OSI Approved :: Apache Software License
Classifier: Programming Language :: Python :: 3
Classifier: Programming Language :: Python :: 3.10
Classifier: Programming Language :: Python :: 3.11
Classifier: Programming Language :: Python :: 3.12
Classifier: Programming Language :: Python :: 3.13
Classifier: Programming Language :: Python :: 3.14
Classifier: Topic :: Scientific/Engineering :: Physics
Classifier: Topic :: Software Development :: Libraries :: Python Modules
Requires-Python: <3.15,>=3.10
Requires-Dist: qiskit-code-assistant-mcp-server>=0.2.0
Requires-Dist: qiskit-ibm-runtime-mcp-server>=0.3.0
Requires-Dist: qiskit-ibm-transpiler-mcp-server>=0.2.0
Requires-Dist: qiskit-mcp-server>=0.1.0
Provides-Extra: all
Requires-Dist: qiskit-code-assistant-mcp-server>=0.2.0; extra == 'all'
Requires-Dist: qiskit-ibm-runtime-mcp-server>=0.3.0; extra == 'all'
Requires-Dist: qiskit-ibm-transpiler-mcp-server>=0.2.0; extra == 'all'
Requires-Dist: qiskit-mcp-server>=0.1.0; extra == 'all'
Provides-Extra: code-assistant
Requires-Dist: qiskit-code-assistant-mcp-server>=0.2.0; extra == 'code-assistant'
Provides-Extra: qiskit
Requires-Dist: qiskit-mcp-server>=0.1.0; extra == 'qiskit'
Provides-Extra: runtime
Requires-Dist: qiskit-ibm-runtime-mcp-server>=0.2.0; extra == 'runtime'
Provides-Extra: transpiler
Requires-Dist: qiskit-ibm-transpiler-mcp-server>=0.2.0; extra == 'transpiler'
